comet_core/__init__.py
comet_core/api.py
comet_core/api_helper.py
comet_core/api_v0.py
comet_core/app.py
comet_core/data_store.py
comet_core/exceptions.py
comet_core/fingerprint.py
comet_core/model.py
comet_core/plugin_interface.py
comet_core-2.11.0.dist-info/LICENSE
comet_core-2.11.0.dist-info/METADATA
comet_core-2.11.0.dist-info/WHEEL
comet_core-2.11.0.dist-info/top_level.txt
comet_core-2.11.0.dist-info/RECORD
