Metadata-Version: 2.1
Name: comet-core
Version: 2.11.0
Summary: Comet Distributed Security Notification Framework
Home-page: https://github.com/spotify/comet-core
Author: Spotify Platform Security
Author-email: wasabi@spotify.com
License: UNKNOWN
Platform: UNKNOWN
Classifier: Development Status :: 5 - Production/Stable
Classifier: Programming Language :: Python
Classifier: Programming Language :: Python :: 3
Classifier: Programming Language :: Python :: 3.6
Classifier: Programming Language :: Python :: 3.7
Classifier: Programming Language :: Python :: 3.8
Classifier: Programming Language :: Python :: 3.9
Requires-Dist: Flask (~=2.0)
Requires-Dist: Flask-Cors (~=3.0)
Requires-Dist: SQLAlchemy (~=1.4)
